more_kedro/__init__.py
more_kedro/datasets.py
more_kedro/hooks.py
more_kedro-0.2.0.dist-info/LICENSE
more_kedro-0.2.0.dist-info/METADATA
more_kedro-0.2.0.dist-info/WHEEL
more_kedro-0.2.0.dist-info/top_level.txt
more_kedro-0.2.0.dist-info/RECORD
