Metadata-Version: 2.1
Name: more-kedro
Version: 0.2.0
Summary: A collection of utilities and extensions for Kedro
Home-page: https://github.com/jonathanlofgren/more-kedro
Author: Jonathan Löfgren
Author-email: lofgren021@gmail.com
License: UNKNOWN
Platform: UNKNOWN
Classifier: License :: OSI Approved :: MIT License
Classifier: Operating System :: OS Independent
Classifier: Intended Audience :: Developers
Classifier: Natural Language :: English
Classifier: Programming Language :: Python :: 3.6
Classifier: Programming Language :: Python :: 3.7
Classifier: Programming Language :: Python :: 3.8
Requires-Python: >=3.6
Requires-Dist: kedro (>=0.16.0)
